pedil/__init__.py
pedil/pedil.py
pedil-0.1.1.dist-info/METADATA
pedil-0.1.1.dist-info/WHEEL
pedil-0.1.1.dist-info/top_level.txt
pedil-0.1.1.dist-info/RECORD
