Metadata-Version: 2.1
Name: pedil
Version: 0.1.1
Summary: A Python package for generating unique and secure IDs using Prime Extended Decimal Index Listing (PEDIL).
Home-page: https://github.com/yourusername/pedil
Author: Ire Gaddr
Author-email: iregaddr@gmail.com
Classifier: Programming Language :: Python :: 3
Classifier: License :: OSI Approved :: MIT License
Classifier: Operating System :: OS Independent
Requires-Python: >=3.6
Requires-Dist: sympy
